{
  "parent": "minecraft:recipes/root",
  "criteria": {
    "has_end_crystal": {
      "conditions": {
        "items": [
          {
            "items": [
              "minecraft:end_crystal"
            ]
          }
        ]
      },
      "trigger": "minecraft:inventory_changed"
    },
    "has_refined_shard": {
      "conditions": {
        "items": [
          {
            "items": [
              "trimmersmp:refined_shard"
            ]
          }
        ]
      },
      "trigger": "minecraft:inventory_changed"
    },
    "has_the_recipe": {
      "conditions": {
        "recipe": "trimmersmp:harness_crystal"
      },
      "trigger": "minecraft:recipe_unlocked"
    }
  },
  "requirements": [
    [
      "has_end_crystal",
      "has_refined_shard",
      "has_the_recipe"
    ]
  ],
  "rewards": {
    "recipes": [
      "trimmersmp:harness_crystal"
    ]
  },
  "sends_telemetry_event": false
}